vintager/__init__.py
vintager/vintager.py
vintager-0.1.3.dist-info/METADATA
vintager-0.1.3.dist-info/WHEEL
vintager-0.1.3.dist-info/entry_points.txt
vintager-0.1.3.dist-info/RECORD
