Metadata-Version: 2.4
Name: vintager
Version: 0.1.3
Summary: A Python package for applying vintage effects to images.
Project-URL: Homepage, https://github.com/Fran-98/vintager
Project-URL: Issues, https://github.com/Fran-98/vintager/issues
Author-email: Fran-98 <franciscopvargas98@gmail.com>
License-Expression: MIT
Classifier: Operating System :: OS Independent
Classifier: Programming Language :: Python :: 3
Requires-Python: >=3.6
Requires-Dist: numpy
Requires-Dist: pillow
